mcodac.libs/libgfortran-93980b03.so.5.0.0
mcodac.libs/libquadmath-776d53b6.so.0.0.0
mcodac.libs/libblas-fe34f726.so.3.8.0
mcodac.libs/liblapack-31d7d384.so.3.8.0
mcodac-1.2.0.dist-info/METADATA
mcodac-1.2.0.dist-info/WHEEL
mcodac-1.2.0.dist-info/LICENSE
mcodac-1.2.0.dist-info/RECORD
mcodac/_mcodac.cpython-311-x86_64-linux-gnu.so
mcodac/__init__.py
